{
  "updatedAt": "2025-11-18T00:14:17.785Z",
  "rates": {
    "TWD": 1,
    "AED": 0.1179,
    "AFN": 2.129,
    "ALL": 2.6721,
    "AMD": 12.2742,
    "ANG": 0.05746,
    "AOA": 30.0889,
    "ARS": 44.9728,
    "AUD": 0.04938,
    "AWG": 0.05746,
    "AZN": 0.05456,
    "BAM": 0.05411,
    "BBD": 0.0642,
    "BDT": 3.9202,
    "BGN": 0.05411,
    "BHD": 0.01207,
    "BIF": 94.4316,
    "BMD": 0.0321,
    "BND": 0.04178,
    "BOB": 0.2222,
    "BRL": 0.1703,
    "BSD": 0.0321,
    "BTN": 2.8458,
    "BWP": 0.4468,
    "BYN": 0.1094,
    "BZD": 0.0642,
    "CAD": 0.04503,
    "CDF": 70.5875,
    "CHF": 0.02553,
    "CLF": 0.00075342,
    "CLP": 29.7799,
    "CNH": 0.2279,
    "CNY": 0.2288,
    "COP": 120.6736,
    "CRC": 16.0856,
    "CUP": 0.7704,
    "CVE": 3.0506,
    "CZK": 0.6683,
    "DJF": 5.7049,
    "DKK": 0.2064,
    "DOP": 2.0651,
    "DZD": 4.1816,
    "EGP": 1.5096,
    "ERN": 0.4815,
    "ETB": 5.0128,
    "EUR": 0.02767,
    "FJD": 0.07316,
    "FKP": 0.02436,
    "FOK": 0.2064,
    "GBP": 0.02436,
    "GEL": 0.08694,
    "GGP": 0.02436,
    "GHS": 0.3582,
    "GIP": 0.02436,
    "GMD": 2.3612,
    "GNF": 279.3663,
    "GTQ": 0.246,
    "GYD": 6.7206,
    "HKD": 0.2493,
    "HNL": 0.8446,
    "HRK": 0.2084,
    "HTG": 4.2069,
    "HUF": 10.6166,
    "IDR": 536.6905,
    "ILS": 0.1046,
    "IMP": 0.02436,
    "INR": 2.8455,
    "IQD": 42.138,
    "IRR": 1400.1677,
    "ISK": 4.0764,
    "JEP": 0.02436,
    "JMD": 5.1547,
    "JOD": 0.02276,
    "JPY": 4.9734,
    "KES": 4.1534,
    "KGS": 2.8094,
    "KHR": 129.1797,
    "KID": 0.04938,
    "KMF": 13.6107,
    "KRW": 46.9314,
    "KWD": 0.009778,
    "KYD": 0.02675,
    "KZT": 16.7717,
    "LAK": 698.614,
    "LBP": 2872.994,
    "LKR": 9.8242,
    "LRD": 5.8243,
    "LSL": 0.5498,
    "LYD": 0.1752,
    "MAD": 0.2965,
    "MDL": 0.5409,
    "MGA": 144.3866,
    "MKD": 1.7103,
    "MMK": 67.3109,
    "MNT": 114.382,
    "MOP": 0.2568,
    "MRU": 1.279,
    "MUR": 1.4701,
    "MVR": 0.4959,
    "MWK": 55.988,
    "MXN": 0.5898,
    "MYR": 0.1331,
    "MZN": 2.051,
    "NAD": 0.5498,
    "NGN": 46.2355,
    "NIO": 1.1813,
    "NOK": 0.324,
    "NPR": 4.5533,
    "NZD": 0.05671,
    "OMR": 0.01234,
    "PAB": 0.0321,
    "PEN": 0.108,
    "PGK": 0.1358,
    "PHP": 1.8932,
    "PKR": 9.0607,
    "PLN": 0.117,
    "PYG": 227.0898,
    "QAR": 0.1168,
    "RON": 0.1411,
    "RSD": 3.2397,
    "RUB": 2.6038,
    "RWF": 46.876,
    "SAR": 0.1204,
    "SBD": 0.2647,
    "SCR": 0.475,
    "SDG": 14.5881,
    "SEK": 0.3037,
    "SGD": 0.04178,
    "SHP": 0.02436,
    "SLE": 0.7481,
    "SLL": 748.0916,
    "SOS": 18.3191,
    "SRD": 1.2386,
    "SSP": 151.2896,
    "STN": 0.6778,
    "SYP": 353.3553,
    "SZL": 0.5498,
    "THB": 1.0427,
    "TJS": 0.2978,
    "TMT": 0.1127,
    "TND": 0.0947,
    "TOP": 0.07722,
    "TRY": 1.357,
    "TTD": 0.2177,
    "TVD": 0.04938,
    "TZS": 78.1098,
    "UAH": 1.3504,
    "UGX": 114.4305,
    "USD": 0.0321,
    "UYU": 1.2777,
    "UZS": 392.3822,
    "VES": 7.6026,
    "VND": 842.6465,
    "VUV": 3.9172,
    "WST": 0.08991,
    "XAF": 18.1476,
    "XCD": 0.08667,
    "XCG": 0.05746,
    "XDR": 0.02356,
    "XOF": 18.1476,
    "XPF": 3.3014,
    "YER": 7.6543,
    "ZAR": 0.5498,
    "ZMW": 0.7283,
    "ZWL": 0.8458
  }
}