{
  "updatedAt": "2026-02-19T00:21:01.050Z",
  "rates": {
    "TWD": 1,
    "AED": 0.1167,
    "AFN": 1.9999,
    "ALL": 2.5909,
    "AMD": 11.9922,
    "ANG": 0.05689,
    "AOA": 29.5824,
    "ARS": 46.1539,
    "AUD": 0.04503,
    "AWG": 0.05689,
    "AZN": 0.05411,
    "BAM": 0.05259,
    "BBD": 0.06356,
    "BDT": 3.8861,
    "BGN": 0.05259,
    "BHD": 0.01195,
    "BIF": 94.4163,
    "BMD": 0.03178,
    "BND": 0.04023,
    "BOB": 0.2203,
    "BRL": 0.1661,
    "BSD": 0.03178,
    "BTN": 2.8839,
    "BWP": 0.4229,
    "BYN": 0.09049,
    "BZD": 0.06356,
    "CAD": 0.04344,
    "CDF": 73.5874,
    "CHF": 0.02451,
    "CLF": 0.00069796,
    "CLP": 27.5879,
    "CNH": 0.2195,
    "CNY": 0.2209,
    "COP": 116.1504,
    "CRC": 15.3232,
    "CUP": 0.7627,
    "CVE": 2.9651,
    "CZK": 0.652,
    "DJF": 5.6481,
    "DKK": 0.2006,
    "DOP": 1.9595,
    "DZD": 4.13,
    "EGP": 1.4939,
    "ERN": 0.4767,
    "ETB": 4.9122,
    "EUR": 0.02689,
    "FJD": 0.06989,
    "FKP": 0.02347,
    "FOK": 0.2006,
    "GBP": 0.02347,
    "GEL": 0.08524,
    "GGP": 0.02347,
    "GHS": 0.3507,
    "GIP": 0.02347,
    "GMD": 2.3578,
    "GNF": 278.8314,
    "GTQ": 0.244,
    "GYD": 6.6618,
    "HKD": 0.2484,
    "HNL": 0.8417,
    "HRK": 0.2026,
    "HTG": 4.183,
    "HUF": 10.1812,
    "IDR": 536.695,
    "ILS": 0.09906,
    "IMP": 0.02347,
    "INR": 2.8855,
    "IQD": 41.7166,
    "IRR": 40791.3669,
    "ISK": 3.8959,
    "JEP": 0.02347,
    "JMD": 4.9565,
    "JOD": 0.02253,
    "JPY": 4.8969,
    "KES": 4.1046,
    "KGS": 2.7862,
    "KHR": 127.8839,
    "KID": 0.04503,
    "KMF": 13.2294,
    "KRW": 46.0532,
    "KWD": 0.009688,
    "KYD": 0.02648,
    "KZT": 15.5475,
    "LAK": 684.9193,
    "LBP": 2844.3966,
    "LKR": 9.8421,
    "LRD": 5.9074,
    "LSL": 0.5099,
    "LYD": 0.2007,
    "MAD": 0.2909,
    "MDL": 0.5412,
    "MGA": 137.785,
    "MKD": 1.659,
    "MMK": 66.8739,
    "MNT": 112.7023,
    "MOP": 0.2559,
    "MRU": 1.2724,
    "MUR": 1.4654,
    "MVR": 0.4919,
    "MWK": 55.3683,
    "MXN": 0.5454,
    "MYR": 0.1242,
    "MZN": 2.0347,
    "NAD": 0.5099,
    "NGN": 42.6321,
    "NIO": 1.1711,
    "NOK": 0.3022,
    "NPR": 4.6143,
    "NZD": 0.05314,
    "OMR": 0.01222,
    "PAB": 0.03178,
    "PEN": 0.1064,
    "PGK": 0.1379,
    "PHP": 1.8411,
    "PKR": 8.8842,
    "PLN": 0.1134,
    "PYG": 207.661,
    "QAR": 0.1157,
    "RON": 0.137,
    "RSD": 3.156,
    "RUB": 2.4358,
    "RWF": 46.4767,
    "SAR": 0.1192,
    "SBD": 0.2565,
    "SCR": 0.4459,
    "SDG": 17.3038,
    "SEK": 0.2861,
    "SGD": 0.04023,
    "SHP": 0.02347,
    "SLE": 0.7783,
    "SLL": 778.3116,
    "SOS": 18.1667,
    "SRD": 1.2003,
    "SSP": 145.3204,
    "STN": 0.6588,
    "SYP": 3.6133,
    "SZL": 0.5099,
    "THB": 0.9939,
    "TJS": 0.3002,
    "TMT": 0.1114,
    "TND": 0.09084,
    "TOP": 0.07573,
    "TRY": 1.3902,
    "TTD": 0.2157,
    "TVD": 0.04503,
    "TZS": 82.723,
    "UAH": 1.3788,
    "UGX": 113.0873,
    "USD": 0.03178,
    "UYU": 1.236,
    "UZS": 387.7443,
    "VES": 12.6725,
    "VND": 823.1414,
    "VUV": 3.7951,
    "WST": 0.08598,
    "XAF": 17.6392,
    "XCD": 0.08581,
    "XCG": 0.05689,
    "XDR": 0.02306,
    "XOF": 17.6392,
    "XPF": 3.2089,
    "YER": 7.5861,
    "ZAR": 0.5099,
    "ZMW": 0.5923,
    "ZWG": 0.8137,
    "ZWL": 0.8137
  }
}