{
  "updatedAt": "2026-03-04T00:18:37.377Z",
  "rates": {
    "TWD": 1,
    "AED": 0.1158,
    "AFN": 1.9838,
    "ALL": 2.61,
    "AMD": 11.9237,
    "ANG": 0.05644,
    "AOA": 29.6459,
    "ARS": 45.7912,
    "AUD": 0.04485,
    "AWG": 0.05644,
    "AZN": 0.05368,
    "BAM": 0.05315,
    "BBD": 0.06306,
    "BDT": 3.8635,
    "BGN": 0.05315,
    "BHD": 0.01186,
    "BIF": 93.9999,
    "BMD": 0.03153,
    "BND": 0.04035,
    "BOB": 0.2191,
    "BRL": 0.1663,
    "BSD": 0.03153,
    "BTN": 2.9046,
    "BWP": 0.4315,
    "BYN": 0.09154,
    "BZD": 0.06306,
    "CAD": 0.04317,
    "CDF": 72.1765,
    "CHF": 0.02469,
    "CLF": 0.00070479,
    "CLP": 27.8577,
    "CNH": 0.218,
    "CNY": 0.2209,
    "COP": 119.0134,
    "CRC": 14.8737,
    "CUP": 0.7567,
    "CVE": 2.9966,
    "CZK": 0.6609,
    "DJF": 5.6038,
    "DKK": 0.2027,
    "DOP": 1.8964,
    "DZD": 4.1262,
    "EGP": 1.572,
    "ERN": 0.473,
    "ETB": 4.9517,
    "EUR": 0.02716,
    "FJD": 0.06976,
    "FKP": 0.02369,
    "FOK": 0.2028,
    "GBP": 0.02369,
    "GEL": 0.08573,
    "GGP": 0.02369,
    "GHS": 0.3404,
    "GIP": 0.02369,
    "GMD": 2.3427,
    "GNF": 276.6141,
    "GTQ": 0.2423,
    "GYD": 6.6181,
    "HKD": 0.2462,
    "HNL": 0.8364,
    "HRK": 0.2048,
    "HTG": 4.1466,
    "HUF": 10.4849,
    "IDR": 532.2703,
    "ILS": 0.09752,
    "IMP": 0.02369,
    "INR": 2.9045,
    "IQD": 41.3781,
    "IRR": 41340.5797,
    "ISK": 3.9023,
    "JEP": 0.02369,
    "JMD": 4.9507,
    "JOD": 0.02236,
    "JPY": 4.9742,
    "KES": 4.0753,
    "KGS": 2.7679,
    "KHR": 127.3899,
    "KID": 0.04485,
    "KMF": 13.37,
    "KRW": 46.6252,
    "KWD": 0.009642,
    "KYD": 0.02628,
    "KZT": 15.7261,
    "LAK": 682.5474,
    "LBP": 2822.0446,
    "LKR": 9.7663,
    "LRD": 5.79,
    "LSL": 0.5197,
    "LYD": 0.2007,
    "MAD": 0.2929,
    "MDL": 0.5423,
    "MGA": 132.679,
    "MKD": 1.6674,
    "MMK": 66.2556,
    "MNT": 113.5711,
    "MOP": 0.2539,
    "MRU": 1.2678,
    "MUR": 1.4822,
    "MVR": 0.4881,
    "MWK": 55.1223,
    "MXN": 0.5569,
    "MYR": 0.1245,
    "MZN": 2.0146,
    "NAD": 0.5197,
    "NGN": 43.1269,
    "NIO": 1.1629,
    "NOK": 0.3053,
    "NPR": 4.6474,
    "NZD": 0.05352,
    "OMR": 0.01212,
    "PAB": 0.03153,
    "PEN": 0.1071,
    "PGK": 0.1363,
    "PHP": 1.8445,
    "PKR": 8.8265,
    "PLN": 0.1156,
    "PYG": 204.8836,
    "QAR": 0.1148,
    "RON": 0.1385,
    "RSD": 3.1848,
    "RUB": 2.4488,
    "RWF": 46.2208,
    "SAR": 0.1182,
    "SBD": 0.2531,
    "SCR": 0.4546,
    "SDG": 14.2309,
    "SEK": 0.292,
    "SGD": 0.04031,
    "SHP": 0.02369,
    "SLE": 0.7799,
    "SLL": 779.9043,
    "SOS": 18.0636,
    "SRD": 1.1957,
    "SSP": 144.773,
    "STN": 0.6658,
    "SYP": 3.547,
    "SZL": 0.5197,
    "THB": 1.0008,
    "TJS": 0.3015,
    "TMT": 0.1116,
    "TND": 0.09151,
    "TOP": 0.07584,
    "TRY": 1.3891,
    "TTD": 0.2141,
    "TVD": 0.04485,
    "TZS": 81.2375,
    "UAH": 1.3699,
    "UGX": 116.1602,
    "USD": 0.03153,
    "UYU": 1.2159,
    "UZS": 387.2533,
    "VES": 13.4223,
    "VND": 824.3204,
    "VUV": 3.7541,
    "WST": 0.08532,
    "XAF": 17.8267,
    "XCD": 0.08513,
    "XCG": 0.05644,
    "XDR": 0.02312,
    "XOF": 17.8267,
    "XPF": 3.243,
    "YER": 7.5316,
    "ZAR": 0.5197,
    "ZMW": 0.6042,
    "ZWG": 0.8124,
    "ZWL": 0.8125
  }
}