{
  "updatedAt": "2026-03-16T00:22:53.081Z",
  "rates": {
    "TWD": 1,
    "AED": 0.1144,
    "AFN": 1.9623,
    "ALL": 2.6213,
    "AMD": 11.7723,
    "ANG": 0.05574,
    "AOA": 28.8216,
    "ARS": 45.2197,
    "AUD": 0.04448,
    "AWG": 0.05574,
    "AZN": 0.05308,
    "BAM": 0.05332,
    "BBD": 0.06228,
    "BDT": 3.8372,
    "BGN": 0.05332,
    "BHD": 0.01171,
    "BIF": 92.9035,
    "BMD": 0.03114,
    "BND": 0.04,
    "BOB": 0.2162,
    "BRL": 0.1647,
    "BSD": 0.03114,
    "BTN": 2.886,
    "BWP": 0.4246,
    "BYN": 0.09255,
    "BZD": 0.06228,
    "CAD": 0.04273,
    "CDF": 70.6762,
    "CHF": 0.02463,
    "CLF": 0.00072219,
    "CLP": 28.5453,
    "CNH": 0.2151,
    "CNY": 0.2158,
    "COP": 115.4135,
    "CRC": 14.7279,
    "CUP": 0.7473,
    "CVE": 3.0062,
    "CZK": 0.6668,
    "DJF": 5.5338,
    "DKK": 0.2034,
    "DOP": 1.9187,
    "DZD": 4.1367,
    "EGP": 1.6363,
    "ERN": 0.4671,
    "ETB": 4.8975,
    "EUR": 0.02726,
    "FJD": 0.06938,
    "FKP": 0.02353,
    "FOK": 0.2034,
    "GBP": 0.02353,
    "GEL": 0.0851,
    "GGP": 0.02353,
    "GHS": 0.3382,
    "GIP": 0.02353,
    "GMD": 2.3136,
    "GNF": 273.5538,
    "GTQ": 0.2395,
    "GYD": 6.5247,
    "HKD": 0.2442,
    "HNL": 0.8272,
    "HRK": 0.2054,
    "HTG": 4.0901,
    "HUF": 10.7208,
    "IDR": 527.6517,
    "ILS": 0.09772,
    "IMP": 0.02353,
    "INR": 2.8856,
    "IQD": 40.9012,
    "IRR": 4391.5319,
    "ISK": 3.9368,
    "JEP": 0.02353,
    "JMD": 4.905,
    "JOD": 0.02208,
    "JPY": 4.976,
    "KES": 4.0379,
    "KGS": 2.727,
    "KHR": 124.3761,
    "KID": 0.04446,
    "KMF": 13.4127,
    "KRW": 46.6924,
    "KWD": 0.009539,
    "KYD": 0.02595,
    "KZT": 15.2766,
    "LAK": 676.1493,
    "LBP": 2786.8249,
    "LKR": 9.7057,
    "LRD": 5.7252,
    "LSL": 0.5258,
    "LYD": 0.1989,
    "MAD": 0.2947,
    "MDL": 0.5424,
    "MGA": 129.3878,
    "MKD": 1.6703,
    "MMK": 65.5903,
    "MNT": 111.2292,
    "MOP": 0.2515,
    "MRU": 1.2475,
    "MUR": 1.4469,
    "MVR": 0.4826,
    "MWK": 54.1713,
    "MXN": 0.5579,
    "MYR": 0.1229,
    "MZN": 1.9859,
    "NAD": 0.5258,
    "NGN": 43.3086,
    "NIO": 1.15,
    "NOK": 0.3045,
    "NPR": 4.6176,
    "NZD": 0.05372,
    "OMR": 0.01197,
    "PAB": 0.03114,
    "PEN": 0.1076,
    "PGK": 0.1357,
    "PHP": 1.8622,
    "PKR": 8.7105,
    "PLN": 0.1165,
    "PYG": 203.1612,
    "QAR": 0.1133,
    "RON": 0.139,
    "RSD": 3.2025,
    "RUB": 2.4991,
    "RWF": 45.5594,
    "SAR": 0.1168,
    "SBD": 0.2515,
    "SCR": 0.4511,
    "SDG": 14.2968,
    "SEK": 0.2943,
    "SGD": 0.04,
    "SHP": 0.02353,
    "SLE": 0.7664,
    "SLL": 766.3799,
    "SOS": 17.8222,
    "SRD": 1.1719,
    "SSP": 143.3971,
    "STN": 0.668,
    "SYP": 3.5093,
    "SZL": 0.5258,
    "THB": 1.0103,
    "TJS": 0.3016,
    "TMT": 0.1101,
    "TND": 0.09203,
    "TOP": 0.07519,
    "TRY": 1.3787,
    "TTD": 0.2125,
    "TVD": 0.04446,
    "TZS": 81.2522,
    "UAH": 1.378,
    "UGX": 116.7708,
    "USD": 0.03114,
    "UYU": 1.2557,
    "UZS": 382.5682,
    "VES": 13.9129,
    "VND": 819.001,
    "VUV": 3.743,
    "WST": 0.08608,
    "XAF": 17.8836,
    "XCD": 0.08407,
    "XCG": 0.05574,
    "XDR": 0.02297,
    "XOF": 17.8836,
    "XPF": 3.2534,
    "YER": 7.4482,
    "ZAR": 0.5255,
    "ZMW": 0.6106,
    "ZWG": 0.7925,
    "ZWL": 0.7925
  }
}