{
  "updatedAt": "2025-08-12T12:05:43.310Z",
  "rates": {
    "TWD": 1,
    "AED": 0.1227,
    "AFN": 2.2816,
    "ALL": 2.7915,
    "AMD": 12.8271,
    "ANG": 0.05982,
    "AOA": 31.1689,
    "ARS": 44.4641,
    "AUD": 0.05129,
    "AWG": 0.05982,
    "AZN": 0.05682,
    "BAM": 0.05621,
    "BBD": 0.06684,
    "BDT": 4.0589,
    "BGN": 0.05621,
    "BHD": 0.01257,
    "BIF": 100.0937,
    "BMD": 0.03342,
    "BND": 0.04296,
    "BOB": 0.2311,
    "BRL": 0.1817,
    "BSD": 0.03342,
    "BTN": 2.9314,
    "BWP": 0.4659,
    "BYN": 0.1101,
    "BZD": 0.06684,
    "CAD": 0.04601,
    "CDF": 97.2565,
    "CHF": 0.0271,
    "CLP": 32.3146,
    "CNY": 0.24,
    "COP": 135.627,
    "CRC": 16.9198,
    "CUP": 0.8021,
    "CVE": 3.1688,
    "CZK": 0.7029,
    "DJF": 5.9393,
    "DKK": 0.2144,
    "DOP": 2.0395,
    "DZD": 4.342,
    "EGP": 1.619,
    "ERN": 0.5013,
    "ETB": 4.6621,
    "EUR": 0.02874,
    "FJD": 0.07539,
    "FKP": 0.02486,
    "FOK": 0.2145,
    "GBP": 0.02486,
    "GEL": 0.0901,
    "GGP": 0.02486,
    "GHS": 0.3779,
    "GIP": 0.02486,
    "GMD": 2.4335,
    "GNF": 290.6068,
    "GTQ": 0.2563,
    "GYD": 6.9942,
    "HKD": 0.2621,
    "HNL": 0.8757,
    "HRK": 0.2165,
    "HTG": 4.3791,
    "HUF": 11.3583,
    "IDR": 543.2795,
    "ILS": 0.1141,
    "IMP": 0.02486,
    "INR": 2.9314,
    "IQD": 43.8253,
    "IRR": 1456.3061,
    "ISK": 4.1054,
    "JEP": 0.02486,
    "JMD": 5.3464,
    "JOD": 0.02369,
    "JPY": 4.9434,
    "KES": 4.318,
    "KGS": 2.925,
    "KHR": 134.3424,
    "KID": 0.05129,
    "KMF": 14.1382,
    "KRW": 46.4944,
    "KWD": 0.01016,
    "KYD": 0.02785,
    "KZT": 18.1452,
    "LAK": 724.5314,
    "LBP": 2991.0067,
    "LKR": 10.0461,
    "LRD": 6.7029,
    "LSL": 0.593,
    "LYD": 0.1814,
    "MAD": 0.3021,
    "MDL": 0.5637,
    "MGA": 148.0038,
    "MKD": 1.7751,
    "MMK": 70.241,
    "MNT": 119.2896,
    "MOP": 0.2701,
    "MRU": 1.3389,
    "MUR": 1.5185,
    "MVR": 0.5163,
    "MWK": 58.2855,
    "MXN": 0.6227,
    "MYR": 0.1414,
    "MZN": 2.1359,
    "NAD": 0.593,
    "NGN": 51.2447,
    "NIO": 1.2293,
    "NOK": 0.3418,
    "NPR": 4.6903,
    "NZD": 0.05626,
    "OMR": 0.01285,
    "PAB": 0.03342,
    "PEN": 0.1178,
    "PGK": 0.1403,
    "PHP": 1.9082,
    "PKR": 9.4808,
    "PLN": 0.1222,
    "PYG": 249.5808,
    "QAR": 0.1216,
    "RON": 0.1455,
    "RSD": 3.3629,
    "RUB": 2.6644,
    "RWF": 48.5295,
    "SAR": 0.1253,
    "SBD": 0.2811,
    "SCR": 0.4927,
    "SDG": 15.1862,
    "SEK": 0.3216,
    "SGD": 0.04295,
    "SHP": 0.02486,
    "SLE": 0.77,
    "SLL": 769.9501,
    "SOS": 19.122,
    "SRD": 1.2481,
    "SSP": 157.3841,
    "STN": 0.7041,
    "SYP": 431.2986,
    "SZL": 0.593,
    "THB": 1.0829,
    "TJS": 0.3121,
    "TMT": 0.117,
    "TND": 0.09643,
    "TOP": 0.08012,
    "TRY": 1.3598,
    "TTD": 0.2263,
    "TVD": 0.05129,
    "TZS": 84.1828,
    "UAH": 1.3857,
    "UGX": 118.8905,
    "USD": 0.03341,
    "UYU": 1.3392,
    "UZS": 425.1846,
    "VES": 4.4197,
    "VND": 871.3492,
    "VUV": 3.9702,
    "WST": 0.08894,
    "XAF": 18.8509,
    "XCD": 0.09023,
    "XCG": 0.05982,
    "XDR": 0.02445,
    "XOF": 18.8509,
    "XPF": 3.4294,
    "YER": 8.0349,
    "ZAR": 0.5929,
    "ZMW": 0.7813,
    "ZWL": 0.894
  }
}